LICENSE
nino/__init__.py
nino/client.py
nino/fields.py
nino/http.py
nino/models.py
nino/paginator.py
nino/query.py
nino-0.2.4.dist-info/LICENSE
nino-0.2.4.dist-info/WHEEL
nino-0.2.4.dist-info/METADATA
nino-0.2.4.dist-info/RECORD
